libp2p_pyrust-0.1.0.dist-info/METADATA
libp2p_pyrust-0.1.0.dist-info/WHEEL
libp2p_pyrust-0.1.0.dist-info/licenses/LICENSE
libp2p_pyrust/__init__.py
libp2p_pyrust/libp2p_pyrust.cpython-38-aarch64-linux-gnu.so
libp2p_pyrust-0.1.0.dist-info/RECORD
