Metadata-Version: 2.4
Name: libp2p-pyrust
Version: 0.1.0
Classifier: Development Status :: 5 - Production/Stable
Classifier: Programming Language :: Python
Classifier: Programming Language :: Python :: 3
Classifier: Programming Language :: Python :: 3 :: Only
Classifier: Programming Language :: Python :: 3.8
Classifier: Programming Language :: Python :: 3.9
Classifier: Programming Language :: Python :: 3.10
Classifier: Programming Language :: Python :: 3.11
Classifier: Programming Language :: Python :: 3.12
Classifier: Programming Language :: Rust
Classifier: Intended Audience :: Developers
Classifier: Intended Audience :: Information Technology
Classifier: Intended Audience :: System Administrators
Classifier: License :: OSI Approved :: MIT License
Classifier: Operating System :: OS Independent
Classifier: Operating System :: Unix
Classifier: Operating System :: POSIX :: Linux
Classifier: Operating System :: MacOS
Classifier: Operating System :: Microsoft :: Windows
Classifier: Environment :: Console
Classifier: Topic :: Software Development :: Libraries :: Python Modules
Classifier: Topic :: Internet
Classifier: Topic :: System :: Networking
Classifier: Topic :: Communications
License-File: LICENSE
Summary: Python bindings for libp2p implemented in Rust
Author: Anastasios Kaltakis <anastasioskaltakis@gmail.com>
Author-email: Anastasios Kaltakis <anastasioskaltakis@gmail.com>
License: MIT
Requires-Python: >=3.8
Project-URL: Homepage, https://github.com/anaskalt/libp2p-pyrust
Project-URL: Documentation, https://github.com/anaskalt/libp2p-pyrust#readme
Project-URL: Repository, https://github.com/anaskalt/libp2p-pyrust
Project-URL: Bug Reports, https://github.com/anaskalt/libp2p-pyrust/issues
Project-URL: Changelog, https://github.com/anaskalt/libp2p-pyrust/blob/main/CHANGELOG.md
